{
  "entity_type": "area",
  "entity_id": 39,
  "entity_name": "坂東",
  "keyword": "坂東 メンズエステ",
  "results": [
    {
      "position": 1,
      "title": "茨城/坂東市内の総合エステランキング（メンエス・アジアンエステ）",
      "url": "https://www.esthe-ranking.jp/tsukuba/bando-city/all/",
      "description": "信頼と実績メンズエステZERO古河。お客様第一主義、18歳セラピストさんから若妻さんまで高級店なみの施術でおもてなし！毎日お得な割引コースあり！",
      "domain": "www.esthe-ranking.jp"
    },
    {
      "position": 2,
      "title": "タイスマイル | 茨城 坂東 タイ古式マッサージ",
      "url": "https://thaismile-thaimassage.com/",
      "description": "茨城県坂東市辺田、坂東市役所から徒歩9分・車2分 です。お休みにリラックスできる場所です。マッサージしながらストレッチできるタイ古式マッサージ！",
      "domain": "thaismile-thaimassage.com"
    },
    {
      "position": 3,
      "title": "坂東市のエステ情報（メンズエステ・風俗エステ・アジアンエステ）",
      "url": "https://www.es-navi.com/list/list.php?city=08228",
      "description": "坂東市のメンズエステ、アジアンエステ、風俗エステを多数掲載 ！美女が優しく癒やしてくれるエステの優良店から、あなた好みのお店を見つけていただけます。",
      "domain": "www.es-navi.com"
    },
    {
      "position": 4,
      "title": "坂東市でメンズ脱毛が人気のエステサロン",
      "url": "https://beauty.hotpepper.jp/genre/kgkw180/pre08/city22800000/",
      "description": "坂東市のメンズ脱毛が人気のエステサロン検索・予約 · Beauty Lounge M ～愛すべき人がいて～ MORIYA · YOLO 梅郷店 · salonE・C・L・A T【サロンエクラ】 · メンズビューティー ...",
      "domain": "beauty.hotpepper.jp"
    },
    {
      "position": 5,
      "title": "茨城/坂東市に出張可能なアロママッサージサービスのある ...",
      "url": "https://www.esthe-ranking.jp/hakenmassage/08228/ippan/aroma-massage/",
      "description": "つくばメンズエステ TIARA（ティアラ） · 研究学園駅徒歩3分 · 09:00～翌 06:00 · 60分⁄ 14,000円～ · 080-4401-7284電話をかける ...",
      "domain": "www.esthe-ranking.jp"
    },
    {
      "position": 6,
      "title": "古河・結城・坂東のメンズエステ求人一覧｜メンエスリクルート",
      "url": "https://esthe-r.com/?m=shop/index&region=3&pref=8&area=179",
      "description": "坂東市でのメンズエステの仕事は、このような歴史的な背景と観光地の中で成長し、多様な客層とのコミュニケーションを深めるチャンスを提供します。 自然と文化が豊かな坂 ...",
      "domain": "esthe-r.com"
    },
    {
      "position": 7,
      "title": "茨城/坂東市に出張可能な洗体エステ（泡洗体）サービスのある ...",
      "url": "https://www.esthe-ranking.jp/hakenmassage/08228/ippan/sentaiesthe/",
      "description": "信頼と実績メンズエステZERO古河。 お客様第一主義、18歳セラピストさんから若妻さんまで高級店なみの施術でおもてなし！ 毎日お得な割引コースあり！",
      "domain": "www.esthe-ranking.jp"
    },
    {
      "position": 8,
      "title": "【メンズエステが得意な】坂東市でクーポンが ... - Beauty Park",
      "url": "https://www.beauty-park.jp/esthe/coupon/ibaraki/bando-shi/mensesthetic/",
      "description": "茨城県坂東市の「メンズエステが得意な」でクーポンがあるエステサロンを多数掲載 。豊富な店舗数と最新の口コミ情報が充実したビューティーパークでは、地域、 ...",
      "domain": "www.beauty-park.jp"
    },
    {
      "position": 9,
      "title": "常磐線 周辺のメンズエステ1",
      "url": "https://go-mensesthe.net/category/joban/",
      "description": "常磐線 周辺にある日本人メンズエステ・アジアンエステ店の評価・評判・感想・レビュー等の口コミ情報。常磐線 周辺のメンズエステに行くなら読め！行ったら書け！",
      "domain": "go-mensesthe.net"
    },
    {
      "position": 10,
      "title": "坂東スマイル | オイルマッサージメンズエステ日記",
      "url": "https://ameblo.jp/max00711/entry-12830334835.html",
      "description": "2023/11/27 — 遅ればせながらタイ古式マッサージにハマり. 地元でも満足はしていたのですが. 情報共有したいと思いブログ始めました. 手始めに坂東にあるスマイルの ...",
      "domain": "ameblo.jp"
    }
  ]
}