{
  "entity_type": "salon",
  "entity_id": 6258,
  "entity_name": "ベロサボン",
  "keyword": "ベロサボン 口コミ",
  "results": [
    {
      "position": 1,
      "title": "BELLO SAVON（ベロサボン）京橋の口コミ体験談",
      "url": "https://osaka-m.heteml.net/shop/261/",
      "description": "サボンのような良い香りに包まれた完全個室のプライベート空間で、大人の女性の色香を感じながら日々の疲れを癒していただけます。京橋駅北口から徒歩4分の好立地で、10:00 ...",
      "domain": "osaka-m.heteml.net"
    },
    {
      "position": 2,
      "title": "ベロサボン (BELLO SAVON) 京橋の口コミ体験談 - メンエス",
      "url": "https://men-esthe.jp/salon.php?id=12249",
      "description": "3回目の訪問です。 京橋駅近くのルームでアクセスも非常に良いです。 時間ちょうどにインターホンを鳴らし、返事があり、入室。 裏オプションなどはなく、90分15000円を ...",
      "domain": "men-esthe.jp"
    },
    {
      "position": 3,
      "title": "BELLO SAVON(ベロサボン)@京橋 - 大阪メンエス・リフレ・癒し ...",
      "url": "https://bakusai.com/thr_res/acode=7/ctgid=136/bid=1714/tid=11636469/",
      "description": "「BELLO SAVON(ベロサボン)@京橋」は爆サイ.com大阪版の大阪メンエス・リフレ・癒し・お店掲示板で今人気の話題です。「>>155本人に聞いた…",
      "domain": "bakusai.com"
    },
    {
      "position": 4,
      "title": "【BELLO SAVON(ベロサボン)京橋】で働く女性の口コミ・評判",
      "url": "https://menesth-job.jp/25/shop/34768/kuchikomi/",
      "description": "在籍している女の子のクチコミ ... 求人内容は比較的にちゃんとしています！ 内容は求人の概要通りです！ ... スタッフさんの対応もめっちゃしっかりしています！ 相談事があれば ...",
      "domain": "menesth-job.jp"
    },
    {
      "position": 5,
      "title": "BELLO SAVON(ベロサボン)（京橋）の口コミ",
      "url": "https://eslove.jp/shop/31261/review",
      "description": "心さん良かった〜 . メンエスってのを堪能できました。 ルームも綺麗ですしいい時間を過ごせました。 心さんパネル以上のスタイルで綺麗すぎました。",
      "domain": "eslove.jp"
    },
    {
      "position": 6,
      "title": "BELLO SAVON | 京橋・南森町・天満",
      "url": "https://estama.jp/shop/38513/",
      "description": "REVIEW口コミ ; 2026/01/16 (2回～4回) · 5.0. ルックスS級：5.0 · 一級品！！ ; 2025/12/16 (2回～4回) · 5.0. ルックスS級：5.0 · 2回目の利用 ; 2025/11/20 (初めて) · 4.9. ルックスS ...",
      "domain": "estama.jp"
    },
    {
      "position": 7,
      "title": "BELLO SAVON（ベロサボン）｜京橋メンズエステ｜チョイエス",
      "url": "https://osaka.choi-es.com/shop/bello-savon/",
      "description": "施術はオーソドックスな、指圧→オイル→カエル足→4TBとありマッサージ自体もかなり上手いです 。 また会話も色々話題を振ってくれ盛り上げて頂けます。 ただkwkwまで来...",
      "domain": "osaka.choi-es.com"
    },
    {
      "position": 8,
      "title": "メンズエステBELLO SAVON",
      "url": "https://bellosavon.com/",
      "description": "大阪京橋のメンズエステ【BELLO SAVON-ベロサボン-】 美しく、透明感ある純粋無垢なセラピストと、サボンのような良い香りにふわりと優しく包まれ、心落ち着く清潔なルーム ...",
      "domain": "bellosavon.com"
    },
    {
      "position": 9,
      "title": "BELLO SAVON ～ベロサボン～の口コミ投稿",
      "url": "https://www.es-navi.com/review/post.php?sid=054028",
      "description": "京橋駅北口のメンズエステ「BELLO SAVON ～ベロサボン～」への口コミを募集しています。ご利用された感想などをお寄せください。",
      "domain": "www.es-navi.com"
    },
    {
      "position": 10,
      "title": "BELLO SAVON｜大阪 京橋駅｜メンズエステ",
      "url": "https://www.kking.jp/ippan/172775/",
      "description": "最近の口コミ ... 友人が行ってよかったらしいので行ってみました。 なかなかがっつりがよかったです。 コスパも高め！ ... 当サイトは、性的サービスや対価を伴う交際を斡旋・ ...",
      "domain": "www.kking.jp"
    }
  ]
}