{
  "entity_type": "salon",
  "entity_id": 4221,
  "entity_name": "アクアルージュ",
  "keyword": "アクアルージュ 口コミ",
  "results": [
    {
      "position": 1,
      "title": "コフレドール / アクアルージュの口コミ一覧",
      "url": "https://www.cosme.net/products/2952275/review/",
      "description": "【アットコスメ】コフレドール / アクアルージュ（口紅）の口コミ一覧。ユーザーの口コミ（315件）による評判や体験レビューで効果・使用感をチェックできます。",
      "domain": "www.cosme.net"
    },
    {
      "position": 2,
      "title": "メイクアップフォーエバー / アクアルｰジュの口コミ一覧",
      "url": "https://www.cosme.net/products/10046545/review/",
      "description": "少し苦手な匂いがする 。もちはすっごいよくって飲み物飲んだくらいじゃ落ちないです。 口紅とグロスがついてるからこの値段ならコスパはいいんじゃないかな。",
      "domain": "www.cosme.net"
    },
    {
      "position": 3,
      "title": "24 ミネラルアクアルージュ / 24h cosmeの口コミ | おすすめ順",
      "url": "https://lipscosme.com/products/316419/review",
      "description": "色もちはあまりよくないです 。普通の色付きリップみたいに少し擦るとすぐに取れます。 ほどよい保湿力で、薬用リップのようなテクスチャーです。 ベタベタに保湿してくれる ...",
      "domain": "lipscosme.com"
    },
    {
      "position": 4,
      "title": "コフレドール アクアルージュのクチコミ一覧",
      "url": "https://i-voce.jp/cosmetics/512/30194/reviews/",
      "description": "アクアルージュ というだけあり、水っぽく滑らかでツヤツヤ。細かいラメもありグロスのようなきらめきがあります。 発色は普通かな。持ちはイマイチで3，4時間たつとカサカサ ...",
      "domain": "i-voce.jp"
    },
    {
      "position": 5,
      "title": "メイクアップフォーエバー (MAKEUPFOREVER) アクアルージュ [14E ...",
      "url": "https://www.hwahae.com/ja/products/%E3%83%A1%E3%82%A4%E3%82%AF%E3%82%A2%E3%83%83%E3%83%97%E3%83%95%E3%82%A9%E3%83%BC%E3%82%A8%E3%83%90%E3%83%BC-%E3%82%A2%E3%82%AF%E3%82%A2%E3%83%AB%E3%83%BC%E3%82%B8%E3%83%A5-14E-%E3%83%A9%E3%82%A4%E3%83%88%E3%83%AD%E3%83%BC%E3%82%BA%E3%82%A6%E3%83%83%E3%83%89-%E3%82%AB%E3%83%A9%E3%83%BC/1734131/reviews?skin_type=normal",
      "description": "評価 · 4.00 · 色移りしない · 高級感がある · 持続力が高い · ピンク味がある · 色味が良い · オレンジトーンである · 色が鮮やかな ...",
      "domain": "www.hwahae.com"
    },
    {
      "position": 6,
      "title": "アクアルージュウォータープルーフリキッドリップカラー (メイク ...",
      "url": "https://www.ibeautystore.com/products/1028182",
      "description": "高評価の口コミ 3.5点(6件) ... カラーは発色がよくマットな感じですが、透明のグロスを上から塗るとツヤツヤに仕上がり、軽くティッシュオフしても色移りしません。梱包も ...",
      "domain": "www.ibeautystore.com"
    },
    {
      "position": 7,
      "title": "アクアセラムルージュの口コミ",
      "url": "https://www.fancl.co.jp/beauty/reviews/3230c/?srsltid=AfmBOoqrN5i3-nUKJvVx-m8JZE8cW29j_xSLOnktkENFMqJJQVu6qHz8",
      "description": "旧アクアセラムルージュから愛用してますが、発色の良さ、伸びの良さ、落ちにくさなど、ますます良くなっています。特に潤い感が格段にアップしていて、ルージュの塗りやす ...",
      "domain": "www.fancl.co.jp"
    },
    {
      "position": 8,
      "title": "24 ミネラルアクアルージュ / 24h cosmeの口コミ | おすすめ順",
      "url": "https://lipscosme.com/products/316419/review?page=2",
      "description": "24hcosmeのミネラルアクアルージュ（01ベリーローズ）です。するすると塗りやすく、優しく色づいてツヤと潤いをくれます。成分は口に入って大丈夫なように天然成分で作られ ...",
      "domain": "lipscosme.com"
    },
    {
      "position": 9,
      "title": "【楽天市場】口紅 無添加 アクア・アクア オーガニックリッチ ...",
      "url": "https://review.rakuten.co.jp/item/1/232730_10004342/1.1/",
      "description": "ダークチェリーを購入しました。 とてもいい色で気に入りました。 顔色が良く見えます。 身体に優しいのも嬉しいポイントです。 同じシリーズで色々試したいです。",
      "domain": "review.rakuten.co.jp"
    },
    {
      "position": 10,
      "title": "24h cosme / 24 ミネラルアクアルージュの口コミ写真・動画一覧",
      "url": "https://www.cosme.net/products/10146920/photo/",
      "description": "【アットコスメ】24h cosme / 24 ミネラルアクアルージュ（口紅）の口コミ写真・動画一覧。ユーザーの口コミ（86件）と投稿写真・画像で使用感をチェックできます。",
      "domain": "www.cosme.net"
    }
  ]
}