{
  "entity_type": "salon",
  "entity_id": 7649,
  "entity_name": "ゴクウ",
  "keyword": "ゴクウ 口コミ",
  "results": [
    {
      "position": 1,
      "title": "ゴクウ株式会社の評判・口コミ",
      "url": "https://en-hyouban.com/company/10201757224/",
      "description": "給与制度:特にないです 。賞与の付与方法が複雑でした。評価制度:実力主義でした。現在は管理部が以前とは変わってしまったので、年功序列のようになってきつつあります。",
      "domain": "en-hyouban.com"
    },
    {
      "position": 2,
      "title": "口コミ一覧 : 中華風創作ダイニング GOKUH （ゴクウ） - 小川町/ ...",
      "url": "https://tabelog.com/tokyo/A1310/A131002/13304648/dtlrvwlst/?type=0",
      "description": "中華風創作ダイニング GOKUH/ゴクウ (小川町/ダイニングバー)への口コミ です。日本最大級のグルメサイト「食べログ」では、中華風創作ダイニング GOKUH/ゴクウの口コミ23件",
      "domain": "tabelog.com"
    },
    {
      "position": 3,
      "title": "ゴクウの仕事の魅力・やりがい・面白みの口コミ",
      "url": "https://jobtalk.jp/companies/4009795/answers/6407485",
      "description": "トップ層の人物が全方位から信頼が無い 。話を聞かない。大声を上げる。唐突に値切る。協力会社やクライアントにすら「あの人をどうにかしてくれ」と言われる始末。回す能力 ...",
      "domain": "jobtalk.jp"
    },
    {
      "position": 4,
      "title": "【楽天市場】クスリのゴクウ | みんなのレビュー·口コミ",
      "url": "https://review.rakuten.co.jp/review/shop/4/227612_227612/1.0/sort3/",
      "description": "初めての利用でしたが、トラブル無く気持ち良いお買い物でした 。 きめ細やかで丁寧なメールを受注時と発送時に頂いたので、到着まで安心して待つことが出来ました。 今回は ...",
      "domain": "review.rakuten.co.jp"
    },
    {
      "position": 5,
      "title": "ゴクウの 評判・口コミ一覧（全2件）",
      "url": "https://syukatsu-kaigi.jp/companies/109122/word_mouths",
      "description": "株式会社ゴクウの社員・元社員とインターンや選考に参加した学生による、会社の評価と口コミ を公開しています。福利厚生やワークライフバランス、女性の働きやすさなど、気 ...",
      "domain": "syukatsu-kaigi.jp"
    },
    {
      "position": 6,
      "title": "口コミ一覧 : 地鶏屋ごくう 新橋本店 （ゴクウ） - 内幸町/焼き鳥 ...",
      "url": "https://s.tabelog.com/tokyo/A1301/A130103/13037073/dtlrvwlst/?smp=1",
      "description": "鶏肉がぷりぷりで柔らかくて美味しかったです 。 雰囲気も新橋なのに大人な感じで、店員さんの接客も行き届いてました！ お腹いっぱい食べて飲んでこの値段なので、満足です ...",
      "domain": "s.tabelog.com"
    },
    {
      "position": 7,
      "title": "GoCoo (ゴクウ) 梅田の口コミ体験談、評判はどう？ - メンエス",
      "url": "https://men-esthe.jp/salon.php?id=15854",
      "description": "セラピストのスタイル (体型の細さ太さ、胸の大きさ、肌質) スタイルは良いです。また服の上からは分かりにくいですがまあまあ胸はあります。 ただ・・・.",
      "domain": "men-esthe.jp"
    },
    {
      "position": 8,
      "title": "回答者別の社員口コミ（ゴクウ株式会社）",
      "url": "https://en-hyouban.com/company/10201757224/user_kuchikomi/5002307/",
      "description": "給与制度:特にないです。賞与の付与方法が複雑でした。評価制度:実力主義でした。現在は管理部が以前とは変わってしまったので、年功序列のようになってきつつあります。",
      "domain": "en-hyouban.com"
    },
    {
      "position": 9,
      "title": "ゴクウの転職・採用情報｜社員口コミでわかる【転職会議】",
      "url": "https://jobtalk.jp/companies/4009795",
      "description": "企業自体が所謂親族経営で、経営層の身内の意見ばかり優遇し、現場の意見は一切受け入れず、聞く耳を持たなかった。これが原因で現場は疲弊し、無茶なスケジュールを組まれ ...",
      "domain": "jobtalk.jp"
    },
    {
      "position": 10,
      "title": "楽天・シュワブ・高配当株式・米国(四半期決算型)の掲示板",
      "url": "https://finance.yahoo.co.jp/quote/9I312249/forum",
      "description": "頑張ってる投資信託なのに、売りたい50%というのは、当てにならない食べログの評価みたい。 売りたい評価なんかしないで、とっとと売っぱらて消えれば良いのに。 投資 ...",
      "domain": "finance.yahoo.co.jp"
    }
  ]
}