{
  "entity_type": "salon",
  "entity_id": 5370,
  "entity_name": "プリムラ",
  "keyword": "プリムラ 口コミ",
  "results": [
    {
      "position": 1,
      "title": "Primula (プリムラ) 愛知 の口コミ体験談 - メンエス",
      "url": "https://men-esthe.jp/salon.php?id=9179",
      "description": "1.体型は太めですが、胸が大きいので自分的には全然okです。 ... 2.顔は悪くないです、HPの雰囲気とも差がなく悪い印象は感じませんでした。 ... 4.施術はオーソドックスに指圧 ...",
      "domain": "men-esthe.jp"
    },
    {
      "position": 2,
      "title": "アクアスパ (旧プリムラ) 浜松 浜松・掛川の口コミ体験談",
      "url": "https://men-esthe.jp/salon.php?id=5664",
      "description": "笑顔で出迎えてくれました。 体型は細身ではないので、細いのが好きな方にはおすすめできませんが、太いというわけでもないし、胸も服の上から見る限りでも大きそうでした ...",
      "domain": "men-esthe.jp"
    },
    {
      "position": 3,
      "title": "「MarriageSalonプリムラ」の口コミ | 成婚率が高い ...",
      "url": "https://www.nakoudonet.com/nakoudo/hyogo/himeji/109045/review/",
      "description": "プリムラ さんに出会えてよかったです。 今までの結婚相談所のイメージとは違い、気さくで話しやすい仲人さんがおられる、いつでも行きたいと思える結婚相談所です ...",
      "domain": "www.nakoudonet.com"
    },
    {
      "position": 4,
      "title": "体験談「デトックス五郎の揉まれん坊万歳」",
      "url": "https://estama.jp/shop/33696/detox/",
      "description": "Primula(プリムラ)三河は 刈谷市、安城市、豊橋市の完全個室型プライベートサロン ... 私の他に、このお店を体験した方々の 貴重な口コミもバッチリ見つけておきましたよ！",
      "domain": "estama.jp"
    },
    {
      "position": 5,
      "title": "🧖🏻 メンズエステ プリムラ 浜松駅前店 ③ - 静岡メンエス・リフレ ...",
      "url": "https://bakusai.com/thr_res/acode=5/ctgid=136/bid=1713/tid=13038924/",
      "description": "詐欺 好き 地雷 貧乳 寛容 美人 OP 若い かわいい おばさん ババア 釣り 高い 熟女 真面目 デブ 通報 パネマジ ブス 健全 無し 無視 禁止 しっかり スケスケ 上手 会 ...",
      "domain": "bakusai.com"
    },
    {
      "position": 6,
      "title": "プリムラの薬剤師の評判・口コミ・年収一覧 - 薬コミ",
      "url": "https://pcom.mediwis.com/company/22618",
      "description": "この企業の口コミ情報は、まだ投稿されていません。 もし、よろしければ、この企業に関する口コミを投稿してもらえませんか？ ささやかですが、口コミ投稿された方の中 ...",
      "domain": "pcom.mediwis.com"
    },
    {
      "position": 7,
      "title": "【口コミ・評判】プリムラの口コミ・評判 | 愛知県一宮市",
      "url": "https://www.mansion-note.com/mansion/1606268/reviews",
      "description": "駅近で交通や買い物に便利な立地が魅力 。オートロックや暗証番号式エントランスなどセキュリティ面も安心です。共用部や外観はスタイリッシュで綺麗、駐車場も広く使い ...",
      "domain": "www.mansion-note.com"
    },
    {
      "position": 8,
      "title": "【楽天市場】カフェ プリムラ | みんなのレビュー·口コミ",
      "url": "https://review.rakuten.co.jp/review/shop/4/226542_226542/1.1/sort3/",
      "description": "いつ発送か選べたらいいと思います 。 何度もリピートしてますが、注文するタイミングがいまいち掴めずです。 よくスイーツのショップでは○日発送とか選べるようになってる ...",
      "domain": "review.rakuten.co.jp"
    },
    {
      "position": 9,
      "title": "浜松・Primula・小倉の体験談",
      "url": "https://istanbulescortgirl.org/therapist/205815/",
      "description": "今回は、調査団員の静岡県在住のれんさんが、浜松のメンズエステで体験したセラピストさんの印象や対応について詳しくご紹介！",
      "domain": "istanbulescortgirl.org"
    },
    {
      "position": 10,
      "title": "Primula (プリムラ) 愛知の口コミ体験談",
      "url": "https://www.oreno-esthe.com/esthetics/12174/reviews",
      "description": "▶︎スタイルは細め ▶︎胸は普通 ▶︎顔はくたびれた人妻 ▶︎オプションは多々有り ▶︎オプション料金は1,000円〜10,000円 ▶︎総額は23,000円 ▶︎コスパは普通 ▷... 感想. この口コミの続き ...",
      "domain": "www.oreno-esthe.com"
    }
  ]
}