{
  "entity_type": "salon",
  "entity_id": 5915,
  "entity_name": "歌舞伎蝶",
  "keyword": "歌舞伎蝶 口コミ",
  "results": [
    {
      "position": 1,
      "title": "歌舞伎蝶(歌舞伎町)のクチコミ情報",
      "url": "https://go-mensesthe.net/shinjuku/%E6%AD%8C%E8%88%9E%E4%BC%8E%E7%94%BA/%E8%9D%B6-2/",
      "description": "【システム料金】 ネット8k→11k 【セラピスト】 超美人さんに当たって緊張。多分韓【施術内容】 きさくに話してくれる、泡洗から十分な施術もあり回春技術も良い。",
      "domain": "go-mensesthe.net"
    },
    {
      "position": 2,
      "title": "新宿 メンズエステ 歌舞伎蝶 - 東京外国人ﾒﾝｴｽ・ﾘﾌﾚ・癒し・お店",
      "url": "https://bakusai.com/thr_res/acode=3/ctgid=136/bid=5871/tid=7305138/",
      "description": "3年前ほどまでは良かったさらに言うなら、別ビルの1階の店はさらにかわいかったフュージョンスプラッシュ. [ 匿名さん ]. 0 Good! 0 Bad.",
      "domain": "bakusai.com"
    },
    {
      "position": 3,
      "title": "歌舞伎蝶 新宿の口コミ体験談、評判はどう？ - メンエス",
      "url": "https://men-esthe.jp/salon.php?id=4259",
      "description": "チャイエスです。 名前から場所も歌舞伎町です。 ボロめのビルで見覚えあると思ったら店舗名が違うだけで中身は同じお店がいくつかあるようです。",
      "domain": "men-esthe.jp"
    },
    {
      "position": 4,
      "title": "口コミ一覧：新宿メンズエステ歌舞伎蝶（新宿歌舞伎町）",
      "url": "https://www.es-maniax.com/shop/t253310/s_report/",
      "description": "新宿メンズエステ歌舞伎蝶（新宿歌舞伎町アジアンエステ）の口コミ一覧ページです。メンエスユーザーによるリアルなオススメ口コミが4件集まっています。",
      "domain": "www.es-maniax.com"
    },
    {
      "position": 5,
      "title": "口コミ(体験談)｜歌舞伎蝶",
      "url": "https://fujoho.jp/index.php?p=report&id=139880",
      "description": "2020/05/10 — 料金（実際に支払った総額）: 60分 11000円（室料込）; このお店の利用回数: 初めて; 受付からプレイ開始までの流れ: 自宅から歩いて阿佐ヶ谷駅まで行き、 ...",
      "domain": "fujoho.jp"
    },
    {
      "position": 6,
      "title": "新宿 歌舞伎蝶（同志追撃①） - 僕とポコチとエステとあなた",
      "url": "http://pocochi.blog.fc2.com/blog-entry-1457.html",
      "description": "2019/06/22 — ややぽっちゃり体形ながら、お胸もあり顔立ちはすごく整った可愛い系です。 とても好みのタイプでしたので次回指名するとき困るからと名前を聞いており ...",
      "domain": "pocochi.blog.fc2.com"
    },
    {
      "position": 7,
      "title": "歌舞伎蝶｜アジアンエステ店の口コミ・評価｜新宿駅 東口",
      "url": "https://www.es-king.jp/20240/",
      "description": "歌舞伎蝶 新宿駅 東口のアジアンセラピスト（チャイエス） 店舗タイプのサロンで 「歌舞伎蝶」の体験談と口コミページです。",
      "domain": "www.es-king.jp"
    },
    {
      "position": 8,
      "title": "新宿メンズエステ【歌舞伎蝶】 | 新宿で24時間営業のアロマ ...",
      "url": "https://www.kabuki-es.com/",
      "description": "名前に恥じぬ容姿端麗、マナーなどトップクラスの美女が行うマッサージに心から癒されてください。アロマエステ以外にもドライの全身整体、ヘッドマッサージ、フット ...",
      "domain": "www.kabuki-es.com"
    },
    {
      "position": 9,
      "title": "歌舞伎蝶｜新宿駅東口",
      "url": "https://www.kking.jp/ippan/233632/",
      "description": "新宿駅東口で人気のメンズエステサロン、歌舞伎蝶の口コミ・体験談ページです。みんなのレビューで安心検索してみませんか？歌舞伎蝶は店舗の他に出張も行っている ...",
      "domain": "www.kking.jp"
    },
    {
      "position": 10,
      "title": "歌舞伎蝶 | 大津市・草津市",
      "url": "https://estama.jp/shop/47698/",
      "description": "基本情報 ; アクセス. 瀬田駅 ; 営業時間: 11:00～LAST ; 平均予算. 30 分 / 5,000 円 ～ ; 公式ホームページ: https://kabuki-girl.navi.mn/ ...",
      "domain": "estama.jp"
    }
  ]
}