{
  "entity_type": "salon",
  "entity_id": 2459,
  "entity_name": "タイ古式マッサージ ミン ロッブリー",
  "keyword": "タイ古式マッサージ ミン ロッブリー 口コミ",
  "results": [
    {
      "position": 1,
      "title": "タイ古式マッサージ ミン ロッブリー(タイコシキマッサージ ...",
      "url": "https://beauty.rakuten.co.jp/s4000053276/kutikomi/",
      "description": "全身ガチガチで、いつもかけ込んでマッサージしてもらってます。 足の部分、ふくろはぎの強い刺激に弱いことをセラピストさんに伝え、きっちり要望に沿って施術して ...",
      "domain": "beauty.rakuten.co.jp"
    },
    {
      "position": 2,
      "title": "クチコミ : タイ古式マッサージ ミン ロッブリー - Yahoo!マップ",
      "url": "https://map.yahoo.co.jp/v3/place/NcRuBEAXCHQ/review",
      "description": "数々のタイマッサージ経験者ですが、ここはベスト3に入ります。コリが酷い自分には良く効きました。自信を持って人に薦めたいレベルです。お茶もお菓子もご馳走さまで ...",
      "domain": "map.yahoo.co.jp"
    },
    {
      "position": 3,
      "title": "タイ古式マッサージ ミン ロッブリー",
      "url": "https://beauty.rakuten.co.jp/s4000053276/",
      "description": "タイ古式マッサージのゆったりした時間は、そうした日頃のだるさやストレスも解消してくれます 。 口コミ. 5.0. 来店者さん / 40代 (男性). とても親切に温かみのある ...",
      "domain": "beauty.rakuten.co.jp"
    },
    {
      "position": 4,
      "title": "タイ古式マッサージ ミン ロッブリー（新宿区歌舞伎町）",
      "url": "https://www.ekiten.jp/shop_94236488/info/2532015/",
      "description": "口コミ : 1件. 写真: 201件 · タイ古式マッサージ ミン ロッブリーのアクセスページに遷移 · マッサージ · リラクゼーションマッサージ · ネット予約 · 日祝OK · 21時以降OK ...",
      "domain": "www.ekiten.jp"
    },
    {
      "position": 5,
      "title": "ミンロッブリー(歌舞伎町)のクチコミ情報",
      "url": "https://go-mensesthe.net/shinjuku/%E6%AD%8C%E8%88%9E%E4%BC%8E%E7%94%BA/%E3%83%9F%E3%83%B3%E3%83%AD%E3%83%83%E3%83%96%E3%83%AA%E3%83%BC/",
      "description": "メンズエステ ミンロッブリー(歌舞伎町)の評価・評判・感想・レビュー等の口コミ情報 公式サイト 電話番号 ミンロッブリー 03-3203-1012 コース料金 営業時間 60分6000 ...",
      "domain": "go-mensesthe.net"
    },
    {
      "position": 6,
      "title": "タイ古式マッサージ ミン ロッブリー - Beauty Park",
      "url": "https://www.beauty-park.jp/shop/678546/staff/16330/",
      "description": "タイマッサージ 歴20年 · 沢山のお店で修業を積みました。 スタッフ皆、腕には自信あります。 ミン ロッブリーの本格タイ古式は一度受けたら癖になりますよ。 また行きたく ...",
      "domain": "www.beauty-park.jp"
    },
    {
      "position": 7,
      "title": "大久保(東京)駅で口コミが多いタイ古式マッサージサロン",
      "url": "https://beauty.rakuten.co.jp/relax/eki756/ks126/tk507/sort4/",
      "description": "朝から営業しているのはありがたいですタイ古式をお願いしましたが、体もかなりほぐれて気持ちよかったです担当の方も明るくとてもリラックスできました。",
      "domain": "beauty.rakuten.co.jp"
    },
    {
      "position": 8,
      "title": "【公式】タイ古式マッサージ ミン ロッブリー | 新宿・歌舞 ...",
      "url": "https://www.minlopburi.com/",
      "description": "ミン ロッブリー の施術は、タイに古くから伝わる伝統医学の一つで、ゆっくりとしたリズムで行う、リラックス効果の高いマッサージです。",
      "domain": "www.minlopburi.com"
    },
    {
      "position": 9,
      "title": "商品 : タイ古式マッサージ ミン ロッブリー - Yahoo!マップ",
      "url": "https://map.yahoo.co.jp/v3/place/NcRuBEAXCHQ/item",
      "description": "【スタッフは皆経験豊富です】. 当店は、本場タイから伝わる古式マッサージの技術を10年以上の修業を通じて磨き上げ... · 【タイ式ではストレッチも行います】 · ストレスの ...",
      "domain": "map.yahoo.co.jp"
    },
    {
      "position": 10,
      "title": "タイ古式マッサージ ミン ロッブリー | Kabukicho Tokyo",
      "url": "https://www.facebook.com/61551468775711/?locale=ja_JP",
      "description": "【心の底から気持ちいいと思えるマッサージに巡り合 っていますか？】 本当に気持ちのいいタイ古式とは、受け側が時間を極 端に短く感じるマッサージです。 施術を受けて30 ...",
      "domain": "www.facebook.com"
    }
  ]
}