{
  "entity_type": "salon",
  "entity_id": 9918,
  "entity_name": "コマダム倶楽部",
  "keyword": "コマダム倶楽部 口コミ",
  "results": [
    {
      "position": 1,
      "title": "コマダム倶楽部 谷9店谷九・上本町の口コミ体験談",
      "url": "https://www.cityheaven.net/osaka/A2702/A270203/komadamu_nihon/reviews/",
      "description": "谷九・上本町待ち合わせ「コマダム倶楽部 谷9店」の口コミ・体験レビューをお届け！シティヘブンネット会員200万人によるリアルな口コミでコマダム倶楽部 谷9店の特徴を",
      "domain": "www.cityheaven.net"
    },
    {
      "position": 2,
      "title": "恵比寿コマダム倶楽部 の口コミ体験談、評判はどう？ - メンエス",
      "url": "https://men-esthe.jp/salon.php?id=6799",
      "description": "ディープリンパ7,000円、衣装チェンジ(BD)5,000円など、総額20,000円前後になります。 一応OP無しも聞きましたが、結構露骨な態度だったのでつかない場合はお察しです。",
      "domain": "men-esthe.jp"
    },
    {
      "position": 3,
      "title": "口コミ（19件）｜コマダム倶楽部 梅田店（梅田/ホテヘル）",
      "url": "https://fujoho.jp/index.php?p=shop_repo_list&id=5240",
      "description": "いつもながら、店からホテル到着までの会話が重要ですですが今回は心配ありませんでした姫が喋る喋るw 人なっこい子でキャピキャピしてます腕組みも密着しながらホテル ...",
      "domain": "fujoho.jp"
    },
    {
      "position": 4,
      "title": "『コマダム倶楽部 梅田』のスレッド検索結果",
      "url": "https://bakusai.com/sch_thr_thread/acode=7/word=%E3%82%B3%E3%83%9E%E3%83%80%E3%83%A0%E5%80%B6%E6%A5%BD%E9%83%A8+%E6%A2%85%E7%94%B0/",
      "description": "コマダム倶楽部 梅田店 りおな. 大阪版; 風俗掲示板; 大阪風俗・個人. 口コミを読んでも絶賛の嵐予約困難嬢のりおな様を語れ！ 最新レス投稿日時：2026/02/20 06:48 209 ...",
      "domain": "bakusai.com"
    },
    {
      "position": 5,
      "title": "【恵比寿コマダム倶楽部】で抜きあり調査【恵比寿・銀座など ...",
      "url": "https://aromafudge.tokyo/69984/",
      "description": "2024/09/28 — 抜きの口コミは無いに等しく、「恵比寿コマダム倶楽部」はミセス系店舗ながら、かなり健全なメンズエステ店のようです。 そのため、期待外れだったと ...",
      "domain": "aromafudge.tokyo"
    },
    {
      "position": 6,
      "title": "【体験談】大阪のホテヘル「コマダム倶楽部谷9店」は本番（基盤 ...",
      "url": "https://junichi-ando.com/komadamu/",
      "description": "2024/01/14 — 大げさではないというのが口コミを見ても明らかです。 テクニックに関してですが、間違いなく熟練の素晴らしいテクニックで男性を喜びの世界に連れて行っ ...",
      "domain": "junichi-ando.com"
    },
    {
      "position": 7,
      "title": "口コミ - コマダム倶楽部 梅田店",
      "url": "https://www.cityheaven.net/osaka/A2701/A270101/komadamu_kita/reviews/",
      "description": "梅田・北新地ホテヘル「コマダム倶楽部 梅田店」の口コミ・体験レビューをお届け！シティヘブンネット会員200万人によるリアルな口コミでコマダム倶楽部 梅田店の特徴を",
      "domain": "www.cityheaven.net"
    },
    {
      "position": 8,
      "title": "コマダム倶楽部 梅田店の在籍キャストの口コミ - 関西 風俗求人",
      "url": "https://kansai.qzin.jp/kitakomadame/reviews/",
      "description": "お給料: たくさんのお客様がお越しになられ、たくさんの女性が出勤されていて、大きなお店だなという感じです。お客様からここは安心だよとも良く伺います。",
      "domain": "kansai.qzin.jp"
    },
    {
      "position": 9,
      "title": "恵比寿コマダム倶楽部",
      "url": "https://estama.jp/shop/33230/",
      "description": "アロマの香りに包まれた個室でリラックス…こんな贅沢な時間は久しぶりです✨丁寧な施術で肩こりもスッキリ！30代になって感じる疲れに効きました  また行きます！",
      "domain": "estama.jp"
    },
    {
      "position": 10,
      "title": "恵比寿コマダム倶楽部（都内広範囲にルームあり）の店舗情報",
      "url": "https://www.es-maniax.com/shop/t1268331/s_top/",
      "description": "恵比寿コマダム倶楽部（都内広範囲にルームあり日本人メンズエステ）の紹介ページです。オススメのセラピスト口コミが2件集まっています。",
      "domain": "www.es-maniax.com"
    }
  ]
}