{
  "entity_type": "salon",
  "entity_id": 6895,
  "entity_name": "愛縁",
  "keyword": "愛縁 口コミ",
  "results": [
    {
      "position": 1,
      "title": "🧖🏻 リラクゼーション愛縁 ② - 愛知外国人ﾒﾝｴｽ・ﾘﾌﾚ・癒し・お店 ...",
      "url": "https://bakusai.com/thr_res/acode=5/ctgid=136/bid=5874/tid=7402357/",
      "description": "好き 元気 高い おばさん 臭い 美脚 若い 美人 ババア 雑 85 92 かわいい 上手い 寛容 オイタ 上手 優しい 肌 いい加減 ブサイク 会いたい 梃子 下手 健全 失礼 怒られ ...",
      "domain": "bakusai.com"
    },
    {
      "position": 2,
      "title": "愛縁 名古屋市南区星崎のリラクゼーションマッサージ",
      "url": "https://www.relaxrelax.jp/sp/shop22727/index.html",
      "description": "ちょっぴり天然な感じで癒し度満点の、あやちゃん！ 魅力あふれる女の子で、優しくて気配りができる女性です♪ 彼女との安らぎタイムを体感してみて下さいねっ ...",
      "domain": "www.relaxrelax.jp"
    },
    {
      "position": 3,
      "title": "愛縁「さえさん」のサービスや評判は？ - メンエス",
      "url": "https://men-esthe.jp/therapist.php?id=331209",
      "description": "誰もが好きになりそうな可愛いセラピストです ☆彡 優しい性格ですごーく癒されます。癒しのオーラ全開です(*^_^*) マッサージも好評！上手ですよ。 ぜひ癒されてくださいね！",
      "domain": "men-esthe.jp"
    },
    {
      "position": 4,
      "title": "愛縁の口コミ投稿",
      "url": "https://www.es-navi.com/review/post.php?sid=005175",
      "description": "本星崎駅のリラクゼーション「愛縁」への口コミを募集しています。ご利用された感想などをお寄せください。",
      "domain": "www.es-navi.com"
    },
    {
      "position": 5,
      "title": "by pakkuri : 愛縁喜宴 本店 - 江戸川橋/居酒屋",
      "url": "https://tabelog.com/tokyo/A1309/A130905/13173908/dtlrvwlst/B187654570/",
      "description": "愛縁 喜宴 本店. 江戸川橋駅/居酒屋､ 日本料理､ 日本酒バー. pakkuriの口コミ詳細. アプリなら口コミがサクサク見られる · pakkuri（4）の口コミ · 認証済. Dinner4.5.",
      "domain": "tabelog.com"
    },
    {
      "position": 6,
      "title": "本星崎 愛縁 070-1675-8181 メンズエステの口コミ・評価",
      "url": "https://www.dino-es.com/massage/shop/KL1ead80174c7f9fb98c2a6d507f914798/",
      "description": "本星崎駅のマッサージ「愛縁」のオススメ・評価・評判・感想・レビュー等の口コミ情報サイトです。お店は中香台（中国人・香港人・台湾人）アジアンの一般エステ、電話番号は ...",
      "domain": "www.dino-es.com"
    },
    {
      "position": 7,
      "title": "クチコミ : 株式会社愛縁喜宴 - 新宿区山吹町/企業・オフィス",
      "url": "https://map.yahoo.co.jp/v3/place/MZDxsZxtj96/review",
      "description": "Rettyユーザーさん. 自然栽培の野菜を使った和食ダイニング。 · Rettyユーザーさん. このお店2回目の投稿です。 · Rettyユーザーさん. 丁寧な仕事で作られる絶品和食のお店。",
      "domain": "map.yahoo.co.jp"
    },
    {
      "position": 8,
      "title": "【25年最新】愛縁舎(那珂市)の評判・口コミ徹底レビュー！",
      "url": "https://www.yanery.com/aiensha-2/",
      "description": "2025/10/17 — 親方さん良い人で見積もり相談もしっかり安心してやってもらえました！塗装で迷っているなら、まずは一度相談オススメです！ 出典 ...",
      "domain": "www.yanery.com"
    },
    {
      "position": 9,
      "title": "有限会社愛縁工芸の 新卒採用・就職・企業情報",
      "url": "https://syukatsu-kaigi.jp/companies/142151",
      "description": "有限会社愛縁工芸の社員・元社員による総合評価は--点です（口コミ回答数1件）。ESや本選考体験記は0件あります。基本情報のほか、有限会社愛縁工芸の社員・元社員による会社 ...",
      "domain": "syukatsu-kaigi.jp"
    },
    {
      "position": 10,
      "title": "口コミ一覧：愛縁喜宴 - Retty（レッティ） 日本最大級の実名型 ...",
      "url": "https://retty.me/area/PRE13/ARE6/SUB604/100001202677/reports/",
      "description": "愛縁喜宴 · オーガニック · 和食居酒屋 · 最高に美味しい · デザートも美味しい · 自然素材にこだわり · 愛情たっぷり · 野菜本来の味をつぶさない · 自家製最高 ...",
      "domain": "retty.me"
    }
  ]
}