{
  "entity_type": "salon",
  "entity_id": 2047,
  "entity_name": "Aroma Lune",
  "keyword": "Aroma Lune 口コミ",
  "results": [
    {
      "position": 1,
      "title": "Lune (ルーン) 中目黒の口コミ体験談、評判はどう？ - メンエス",
      "url": "https://men-esthe.jp/salon.php?id=1872",
      "description": "Lune (ルーン)中目黒の料金、店舗の綺麗さ、施術内容やオイル、サービスの良さ、衣装のエロさ、密着度や事故率、オプション内容を含め徹底調査。2ちゃん、したらば、爆 ...",
      "domain": "men-esthe.jp"
    },
    {
      "position": 2,
      "title": "【事故・過激口コミ】 立川\"AROMA LUNA\"口コミまとめ｜マル秘 ...",
      "url": "https://mens-esthe-info.com/2024/11/29/bakusaimatome_aroma-luna/",
      "description": "2024/11/29 — 本記事は 爆サイ からで 信憑性の高い口コミ のみ抽出(まとめ)しております。 爆サイ本体 を見ていても時間だけ過ぎて情報が入ってこないという無駄な時間 ...",
      "domain": "mens-esthe-info.com"
    },
    {
      "position": 3,
      "title": "口コミ一覧 - AROMA Luna アロマルナ | 宮崎市",
      "url": "https://estama.jp/shop/40020/reviewlist/",
      "description": "マッサージはとても丁寧で、力加減が絶妙 。疲れている箇所を的確に捉えてくれて、身体がじんわり軽くなる感覚が心地よかったです。細やかな気配りとサービス精神も ...",
      "domain": "estama.jp"
    },
    {
      "position": 4,
      "title": "Aroma Luna (アロマルナ) 福岡 福岡・博多の口コミ体験談",
      "url": "https://men-esthe.jp/salon.php?id=6046",
      "description": "口コミ ○スタイル若干肉付きは良いですがほぼ写真のイメージ通りでモデル体型のナイスバディです。 ○ルックスショートカットがよく似合う綺麗系の顔立ちです。 ○オプション ...",
      "domain": "men-esthe.jp"
    },
    {
      "position": 5,
      "title": "宮崎メンエス-AROMA Luna (アロマルナ)｜過激嬢2名の体験談",
      "url": "https://codoc.jp/sites/urame/entries/zl1MNM8X5Q",
      "description": "宮崎のメンズエステ「アロマルナ」の口コミや評判をまとめたレポート です。▷宮崎県のアロマエステ一覧 看板セラピスト あまね (24)かれん (25)えみり (25) 店舗情報 ...",
      "domain": "codoc.jp"
    },
    {
      "position": 6,
      "title": "口コミ情報｜AROMA LUNA（アロマルナ） 立川",
      "url": "https://menesth.jp/8/shop/31454/review/",
      "description": "口コミ一覧・1件 ... 清楚な女子大生ながらも意外なスキルの持ち主！ ... 高級店だし大丈夫だろう……といえど、やや心配だったのと初回につき無難な90分コースをチョイス。 立川 ...",
      "domain": "menesth.jp"
    },
    {
      "position": 7,
      "title": "口コミ：Aroma Luna(アロマルナ)／博多駅周辺",
      "url": "https://eslove.jp/shop/27014/review",
      "description": "受け付けに不満. まず言わせてもらいたのが、受け付けの対応がかなり不満。事前にクーポンを使ってのネット予約したが何も連絡なし、こちらからネット予約してますよと電話 ...",
      "domain": "eslove.jp"
    },
    {
      "position": 8,
      "title": "Aroma LaLuna (アロマラルーナ)の求人に関する口コミ評判",
      "url": "https://men-esthe-job.jp/salon-kuchikomi.php?id=1941",
      "description": "お給料自体は悪くないけど客層やや悪めなので完全業界未経験にはきつい店かも 。部屋自体はどれも新しく綺麗なマンションで水周りも問題なく、WiFiもあってよい。掃除は ...",
      "domain": "men-esthe-job.jp"
    },
    {
      "position": 9,
      "title": "Aroma Lunaの口コミ情報",
      "url": "https://esthe-one.jp/fukuoka/a_8002/recruit/s_lunalun/reviews/",
      "description": "お給料: お給料は他のお店より高いと思います！ 暇な事はほとんどなく稼ぎやすいなといつも感じます保証もあるので安心ですし待機があっても部屋が可愛すぎてウキウキし ...",
      "domain": "esthe-one.jp"
    },
    {
      "position": 10,
      "title": "リュンヌ 日本橋(Lune)",
      "url": "https://beauty.hotpepper.jp/kr/slnH000797940/",
      "description": "5 日前 — ※10件以下の口コミの平均点です。 普通＝3が評価時の基準です。あくまでも個人の感想であり、個人差があります。 平均点は直近1年間の集計です。",
      "domain": "beauty.hotpepper.jp"
    }
  ]
}