{
  "entity_type": "salon",
  "entity_id": 6218,
  "entity_name": "ジャスミン",
  "keyword": "ジャスミン 口コミ",
  "results": [
    {
      "position": 1,
      "title": "サントリー / ジャスミン茶の口コミ一覧",
      "url": "https://www.cosme.net/products/2901889/review/",
      "description": "ジャスミンは香りが好きです 。 普通のお茶を飲むよりオシャレなイメージなところも好き(*^^)v 飲みやすいスッキリとしたジャスミンなのでお気に入りです。",
      "domain": "www.cosme.net"
    },
    {
      "position": 2,
      "title": "No.5 Jasmine Jasmine オーデパルファム 8ml",
      "url": "https://shop.itoen.jp/shop/crazyjasmine/g/gCRJ-66174/?srsltid=AfmBOorvv3Sb2qcPHbw_vJlPt2b2OlUAeEwKdF8kTvf0Wc4EohVM09sa",
      "description": "特別なジャスミンフレグランスです。 シングルノート処方のため、ベースを持たず、つけた瞬間から咲きたての花のようにピュアでみずみずしい香りが広がります。",
      "domain": "shop.itoen.jp"
    },
    {
      "position": 3,
      "title": "【楽天市場】オンラインショップジャスミン - みんなのレビュー",
      "url": "https://review.rakuten.co.jp/rd/0_378138_378138_0/",
      "description": "発送が早くてよかったです 。 もう少し小さいの包装でも良かったかなと思います。 注文日：2025/03/02. 参考になっ ...",
      "domain": "review.rakuten.co.jp"
    },
    {
      "position": 4,
      "title": "ボディスクラブ デリケート ジャスミンのクチコミ・レビュー一覧",
      "url": "https://www.cosmetic-times.com/item/review/list?baseCD=B35403004",
      "description": "使った後の肌がツルツルで気持ちいいです 。 匂いにも癒されます。できたらもっと簡単に蓋が開けたり閉めたりできたら使いやすいと思います。",
      "domain": "www.cosmetic-times.com"
    },
    {
      "position": 5,
      "title": "オンラインショップジャスミンのレビュー - Yahoo!ショッピング",
      "url": "https://shopping.yahoo.co.jp/store_rating/jas-min/store/review/",
      "description": "商品を無事 受け取りました 。 迅速で丁寧な対応をして頂き大変感謝しています。とても信頼できる出品者様で終始安心して お取引きする事ができました。",
      "domain": "shopping.yahoo.co.jp"
    },
    {
      "position": 6,
      "title": "口コミ | ジャスミンスキンクリニック(Jasmine Skin Clinic)",
      "url": "https://clinic.beauty.hotpepper.jp/H000751392/reviews/",
      "description": "近所にできた新しいクリニックでとても綺麗なクリニックだなぁ～と思っていましたが、院内も綺麗で明るく待合室も広いです。受付の皆さんもとても美しく、丁寧に案内もして ...",
      "domain": "clinic.beauty.hotpepper.jp"
    },
    {
      "position": 7,
      "title": "株式会社ジャスミンの口コミ一覧",
      "url": "https://en-hyouban.com/company/10014449810/kuchikomi/",
      "description": "給与水準：派遣からスタートしたが、月収で約30万＋インセンティブ。契約が取れればその都度給与は上がるので満足。 もちろん残業代、交通費は全額支給と福利厚生も問題無し ...",
      "domain": "en-hyouban.com"
    },
    {
      "position": 8,
      "title": "【購入レビュー】クレイジージャスミンの香りはどう？話題の ...",
      "url": "https://www.roomie.jp/2026/01/1701584/",
      "description": "2026/02/01 — 私が知っているジャスミンの香りに一番近く、清涼感さえ感じるほどフレッシュな「No.1」を選ぶことに。この香りに触れると、気持ちまでスッキリと整う気が ...",
      "domain": "www.roomie.jp"
    },
    {
      "position": 9,
      "title": "ディオール / ジャスミン デ ザンジュ オードゥ パルファンの口コミ ...",
      "url": "https://www.cosme.net/products/10144176/review/",
      "description": "他の香りを購入したときに、ミニボトルプレゼントがあったので選びました！ ジャスミン系のなかではかなり華やかというか、スッキリした感じがします！",
      "domain": "www.cosme.net"
    },
    {
      "position": 10,
      "title": "ジャスミンの口コミ21件",
      "url": "https://www.booking.com/reviews/jp/hotel/ziyasumin.ja.html",
      "description": "清潔で、アメニティも豊富で設備が整っていて、キッチン用品は特に何でもあるので助かった。駐車場も3台利用したが、無料でたくさん停めれてありがたかった。メールでの ...",
      "domain": "www.booking.com"
    }
  ]
}